posto_mcp/__init__.py
posto_mcp/__main__.py
uvx_posto_mcp-0.1.0.dist-info/METADATA
uvx_posto_mcp-0.1.0.dist-info/WHEEL
uvx_posto_mcp-0.1.0.dist-info/entry_points.txt
uvx_posto_mcp-0.1.0.dist-info/top_level.txt
uvx_posto_mcp-0.1.0.dist-info/RECORD
