Metadata-Version: 2.4
Name: uvx-posto-mcp
Version: 0.1.0
Summary: UVX-compatible MCP server for Posto social media integration
Author-email: Your Name <your.email@example.com>
Requires-Python: >=3.8
Requires-Dist: posto-sdk>=0.1.0
Requires-Dist: mcp>=1.5.0
